{
  "designerVersion" : "1.7.38",
  "id" : "instantiationForm",
  "name" : "instantiationForm",
  "lastUpdate" : 1525353407731,
  "rows" : [ [ {
    "type" : "formContainer",
    "dimension" : {
      "xs" : 12
    },
    "propertyValues" : { },
    "reference" : "66a1a336-e506-42f4-b296-343411b33e59",
    "id" : "pbFormContainer",
    "container" : {
      "type" : "container",
      "dimension" : {
        "xs" : 12
      },
      "propertyValues" : { },
      "reference" : "1fa9b5ff-7c11-4de5-845c-387db99cc489",
      "id" : "pbContainer",
      "rows" : [ [ {
        "type" : "component",
        "dimension" : {
          "md" : 12,
          "sm" : 12,
          "xs" : 12,
          "lg" : 12
        },
        "propertyValues" : {
          "removeItem" : {
            "type" : "variable"
          },
          "cssClasses" : {
            "type" : "constant",
            "value" : ""
          },
          "widgetId" : {
            "type" : "constant",
            "value" : "pbButton"
          },
          "buttonStyle" : {
            "type" : "constant",
            "value" : "primary"
          },
          "isDisplayed" : {
            "type" : "constant",
            "value" : true
          },
          "label" : {
            "type" : "interpolation",
            "value" : "Submit"
          },
          "dataToSend" : {
            "type" : "expression",
            "value" : "formOutput"
          },
          "labelHidden" : {
            "type" : "constant",
            "value" : false
          },
          "readonly" : {
            "type" : "constant",
            "value" : false
          },
          "collectionPosition" : {
            "type" : "constant"
          },
          "targetUrlOnSuccess" : {
            "type" : "interpolation",
            "value" : "/bonita"
          },
          "action" : {
            "type" : "constant",
            "value" : "Start process"
          },
          "collectionToModify" : {
            "type" : "variable"
          },
          "valueToAdd" : {
            "type" : "expression"
          },
          "disabled" : {
            "type" : "expression",
            "value" : "$form.$invalid"
          },
          "alignment" : {
            "type" : "constant",
            "value" : "center"
          },
          "class" : {
            "type" : "constant",
            "value" : "org.bonitasoft.web.designer.experimental.parametrizedWidget.ButtonWidget"
          },
          "dimension" : {
            "type" : "constant",
            "value" : 12
          }
        },
        "reference" : "5f76d5b2-58d0-4ec9-8f99-f0519425e62e",
        "id" : "pbButton"
      } ] ]
    }
  } ] ],
  "assets" : [ {
    "id" : "2cb18e42-2e39-4f80-a68b-d838b8669423",
    "name" : "localization.json",
    "type" : "json",
    "order" : 0,
    "external" : false
  }, {
    "id" : "25896d80-bbb2-47d7-b916-c7f3db79c941",
    "name" : "style.css",
    "type" : "css",
    "order" : 0,
    "external" : false
  } ],
  "inactiveAssets" : [ ],
  "data" : {
    "formInput" : {
      "type" : "json",
      "value" : "{ }",
      "exposed" : false
    },
    "formOutput" : {
      "type" : "expression",
      "value" : "return {\n\n};",
      "exposed" : false
    }
  },
  "uuid" : "4152a899-f1ae-4b8e-9e89-06d65e0a8b5f",
  "type" : "form"
}